setup.py
fileclusters/__init__.py
fileclusters/admin.py
fileclusters/helpers.py
fileclusters/models.py
fileclusters/tests.py
fileclusters/urls.py
fileclusters/views.py
fileclusters.egg-info/PKG-INFO
fileclusters.egg-info/SOURCES.txt
fileclusters.egg-info/dependency_links.txt
fileclusters.egg-info/not-zip-safe
fileclusters.egg-info/requires.txt
fileclusters.egg-info/top_level.txt
fileclusters/migrations/0001_initial.py
fileclusters/migrations/0002_auto__chg_field_component_cluster__chg_field_component_description__ch.py
fileclusters/migrations/__init__.py
fileclusters/templatetags/__init__.py
fileclusters/templatetags/fileclusters_extras.py
utils/__init__.py
utils/cache/__init__.py
utils/cache/backends/__init__.py
utils/cache/backends/memcached.py
utils/cache/backends/memcached14.py
utils/cache/backends/memcached16.py