Metadata-Version: 1.1
Name: fileclusters
Version: 0.0.2
Summary: COMODA Fileclusters
Home-page: UNKNOWN
Author: Pablo Saavedra
Author-email: pablo.saavedra@interoud.com
License: MIT_License.txt
Keywords: fileclusters
Platform: UNKNOWN
Classifier: Development Status :: 4 - Beta
Classifier: Framework :: Django
Classifier: License :: OSI Approved :: MIT License
Classifier: Operating System :: OS Independent
Classifier: Programming Language :: Python
Classifier: Topic :: Software Development :: Libraries :: Python Modules
Classifier: Topic :: Multimedia :: Video
